CheeseLog/__init__.py
CheeseLog/filter.py
CheeseLog/logger.py
CheeseLog/message.py
CheeseLog/progressBar.py
CheeseLog/style.py
cheeselog-2.1.3.dist-info/METADATA
cheeselog-2.1.3.dist-info/WHEEL
cheeselog-2.1.3.dist-info/licenses/LICENSE
cheeselog-2.1.3.dist-info/RECORD
