Metadata-Version: 2.4
Name: CheeseLog
Version: 2.1.3
Summary: 日志系统。可在控制台输出一定格式的、可选颜色的内容，并支持写入指定的日志文件。
Project-URL: Source, https://github.com/CheeseUnknown/CheeseLog
Author-email: Cheese Unknown <cheese@cheese.ren>
License-File: LICENSE
Keywords: log,logger
